{"cameraMode":{"drawMode":0,"name":"Shaded","section":"Shading Mode"},"sceneLighting":true,"audioPlay":false,"sceneViewState":{"showFog":true,"showMaterialUpdate":false,"showSkybox":true,"showFlares":true,"showImageEffects":true,"showParticleSystems":true},"in2DMode":false,"pivot":{"x":221.64674377441407,"y":64.39826965332031,"z":102.23477172851563},"rotation":{"x":0.013498900458216668,"y":0.010498855262994767,"z":-0.00014174329407978803,"w":0.999853789806366},"size":974.383056640625,"orthographic":false}